{
  "tenantId": "pg",
  "moduleName": "tenant",
  "tenants": [{
      "code": "pg.GoalparaOne",
      "name": "Goalpara",
      "description": "Goalpara",
      "pincode": [783101,783121],
      "logoId": "https://in-egov-assets.s3.ap-south-1.amazonaws.com/in.Goalpara1/logo.png",
      "imageId": null,
      "domainUrl": "https://www.upyog.niua.org",
      "type": "CITY",
      "twitterUrl": null,
      "facebookUrl": null,
      "propertyIdEnabled": false,
      "emailId": "goalpara@gmail.com",
      "OfficeTimings": {
        "Mon - Fri": "9.00 AM - 6.00 PM"
      },
      "city": {
        "name": "Goalpara1",
        "localName": null,
        "districtCode": "Goalpara",
        "districtName": null,
        "districtTenantCode": "pg.Goalpara1",
        "regionName": null,
        "ulbGrade": "Municipal Corporation",
        "longitude": 75.5761829,
        "latitude": 31.3260152,
        "shapeFileLocation": null,
        "captcha": null,
        "code": "1013",
        "ddrName": "DDR A"
      },
      "address": "Goalpara Municipal Corporation",
      "contactNumber": "001-2345876"
    },
{
      "code": "pg.NagaonOne",
      "name": "Nagaon",
      "description": "Nagaon",
      "pincode": [782002,782001,782003],
      "logoId": "https://in-egov-assets.s3.ap-south-1.amazonaws.com/in.Nagaon1/logo.png",
      "imageId": null,
      "domainUrl": "https://www.upyog.niua.org",
      "type": "CITY",
      "twitterUrl": null,
      "facebookUrl": null,
      "propertyIdEnabled": false,
      "emailId": "nagaon@gmail.com",
      "OfficeTimings": {
        "Mon - Fri": "9.00 AM - 6.00 PM"
      },
      "city": {
        "name": "Nagaon",
        "localName": null,
        "districtCode": "Nagaon",
        "districtName": null,
        "districtTenantCode": "pg.NagaonOne",
        "regionName": null,
        "ulbGrade": "Municipal Corporation",
        "longitude": 75.5761829,
        "latitude": 31.3260152,
        "shapeFileLocation": null,
        "captcha": null,
        "code": "1013",
        "ddrName": "DDR A"
      },
      "address": "Nagaon Municipal Corporation",
      "contactNumber": "1100"
}
  ]
}
